email_expose/__init__.py
email_expose/expose_consult.py
email_expose-0.1.2.dist-info/LICENSE
email_expose-0.1.2.dist-info/METADATA
email_expose-0.1.2.dist-info/WHEEL
email_expose-0.1.2.dist-info/entry_points.txt
email_expose-0.1.2.dist-info/RECORD
