Metadata-Version: 2.1
Name: email-expose
Version: 0.1.2
Summary: 
License: MIT
Author: Cristiano Henrique
Author-email: cristianovisk@gmail.com
Requires-Python: >=3.10,<4.0
Classifier: License :: OSI Approved :: MIT License
Classifier: Programming Language :: Python :: 3
Classifier: Programming Language :: Python :: 3.10
Classifier: Programming Language :: Python :: 3.11
Requires-Dist: httpx (>=0.26.0,<0.27.0)
Requires-Dist: lxml (>=5.1.0,<6.0.0)
Requires-Dist: openpyxl (>=3.1.2,<4.0.0)
Requires-Dist: pandas (>=2.2.0,<3.0.0)
Requires-Dist: pyarrow (>=15.0.0,<16.0.0)
Requires-Dist: rich (>=13.7.0,<14.0.0)
Requires-Dist: typer (>=0.9.0,<0.10.0)
Project-URL: Bug Tracker, https://github.com/cristianovisk/EmailExpose/issues
Project-URL: Código, https://github.com/cristianovisk/EmailExpose
Project-URL: Documentação, https://github.com/cristianovisk/EmailExpose/blob/main/README.md
